mcp_server_epic_free_games/__init__.py
mcp_server_epic_free_games/__main__.py
mcp_server_epic_free_games/server.py
mcp_epic_free_games-0.1.2.dist-info/METADATA
mcp_epic_free_games-0.1.2.dist-info/WHEEL
mcp_epic_free_games-0.1.2.dist-info/entry_points.txt
mcp_epic_free_games-0.1.2.dist-info/licenses/LICENSE
mcp_epic_free_games-0.1.2.dist-info/RECORD
