Metadata-Version: 2.4
Name: mcp-epic-free-games
Version: 0.1.2
Summary: A Model Context Protocol server for Epic Games Store free games information
Project-URL: Homepage, https://github.com/meethuhu/mcp-epic-free-games
Project-URL: Repository, https://github.com/meethuhu/mcp-epic-free-games
Project-URL: Issues, https://github.com/meethuhu/mcp-epic-free-games/issues
Author-email: meethuhu <meethuhu@example.com>
License: MIT
License-File: LICENSE
Keywords: epic games,free games,mcp,model context protocol
Classifier: Development Status :: 4 - Beta
Classifier: Intended Audience :: Developers
Classifier: License :: OSI Approved :: MIT License
Classifier: Programming Language :: Python :: 3
Classifier: Programming Language :: Python :: 3.13
Classifier: Topic :: Games/Entertainment
Classifier: Topic :: Software Development :: Libraries :: Python Modules
Requires-Python: >=3.13
Requires-Dist: httpx>=0.28.1
Requires-Dist: mcp[cli]>=1.9.4
Requires-Dist: pydantic>=2.0.0
